Metadata-Version: 1.1
Name: django-custom-query
Version: 0.3.0
Summary: Custom user query parser for Django ORM
Home-page: http://django-custom-query.readthedocs.io/
Author: Luis Fagundes
Author-email: lhfagundes@gmail.com
License: The MIT License
Platform: UNKNOWN
Classifier: Intended Audience :: Developers
Classifier: Natural Language :: English
Classifier: Operating System :: OS Independent
Classifier: Programming Language :: Python
Classifier: Topic :: Software Development :: Libraries :: Python Modules
